MANIFEST.in
README.rst
setup.py
django_html_editor.egg-info/PKG-INFO
django_html_editor.egg-info/SOURCES.txt
django_html_editor.egg-info/dependency_links.txt
django_html_editor.egg-info/not-zip-safe
django_html_editor.egg-info/top_level.txt
html_editor/.DS_Store
html_editor/__init__.py
html_editor/decorators.py
html_editor/widgets.py
html_editor/static/.DS_Store
html_editor/static/html_editor/.DS_Store
html_editor/static/html_editor/css/codemirror.css
html_editor/static/html_editor/js/codemirror.js
html_editor/static/html_editor/js/css.js
html_editor/static/html_editor/js/formatting.js
html_editor/static/html_editor/js/htmlmixed.js
html_editor/static/html_editor/js/javascript.js
html_editor/static/html_editor/js/xml.js
html_editor/templates/html_editor/widget.html