Metadata-Version: 1.0
Name: django-html-editor
Version: 0.0.1
Summary: HTML source code editor widget based on CodeMirror JS plugin for Django admin.
Home-page: https://github.com/python33/django_html_editor
Author: Petr Dovnar
Author-email: petrdovnar@gmail.com
License: UNKNOWN
Platform: UNKNOWN
